allcoin/__init__.py
allcoin/client.py
allcoin/exceptions.py
python_allcoin-0.0.1.dist-info/DESCRIPTION.rst
python_allcoin-0.0.1.dist-info/METADATA
python_allcoin-0.0.1.dist-info/RECORD
python_allcoin-0.0.1.dist-info/WHEEL
python_allcoin-0.0.1.dist-info/metadata.json
python_allcoin-0.0.1.dist-info/top_level.txt
