Metadata-Version: 2.0
Name: python-allcoin
Version: 0.0.1
Summary: Allcoin REST API python implementation
Home-page: https://github.com/sammchardy/python-allcoin
Author: Sam McHardy
Author-email: UNKNOWN
License: MIT
Keywords: allcoin exchange rest api bitcoin ethereum btc eth qtum cnet ck.usd
Platform: UNKNOWN
Classifier: Intended Audience :: Developers
Classifier: License :: OSI Approved :: MIT License
Classifier: Operating System :: OS Independent
Classifier: Programming Language :: Python :: 2
Classifier: Programming Language :: Python :: 2.7
Classifier: Programming Language :: Python :: 3
Classifier: Programming Language :: Python :: 3.3
Classifier: Programming Language :: Python :: 3.4
Classifier: Programming Language :: Python :: 3.5
Classifier: Programming Language :: Python :: 3.6
Classifier: Programming Language :: Python
Classifier: Topic :: Software Development :: Libraries :: Python Modules
Requires-Dist: requests
